{
    "search": "leucovorin",
    "explanation": NaN,
    "start_trending": "September 21, 2025 at 12:30:00\u202fPM UTC-7",
    "end_trending": NaN,
    "google_image_prompt": [
        "https://fresenius-kabi.scene7.com/is/image/freseniuskabi/Leucovorin-Calcium-Group?qlt=85&ts=1731462476250&dpr=off",
        "https://www.mcguff.com/content/images/thumbs/0006428_leucovorin-calcium-injection-350-mgvial-single-dose-vial-175-ml-each.jpeg",
        "https://tmedweb.tulane.edu/pharmwiki/lib/exe/fetch.php/leucovorin.png"
    ]
}